pyegps/__init__.py
pyegps/__main__.py
pyegps/_version.py
pyegps/cli.py
pyegps/device.py
pyegps/exceptions.py
pyegps/powerstrip.py
pyegps/fakes/__init__.py
pyegps/fakes/powerstrip.py
pyegps/usb/__init__.py
pyegps/usb/eg_powerstrip.py
pyEGPS-0.2.4.dist-info/LICENSE.md
pyEGPS-0.2.4.dist-info/METADATA
pyEGPS-0.2.4.dist-info/WHEEL
pyEGPS-0.2.4.dist-info/top_level.txt
pyEGPS-0.2.4.dist-info/RECORD
