Metadata-Version: 2.1
Name: pyEGPS
Version: 0.2.4
Summary: Controlling Energenie Power Strips with python.
Author-email: Mischa Siekmann <mischa@gnumpi.com>
License: Apache-2.0
Project-URL: Homepage, https://github.com/gnumpi/pyegps
Classifier: Programming Language :: Python :: 3
Requires-Python: >=3.8
License-File: LICENSE.md
Requires-Dist: pyusb
